{
    "resist_fire": {
        "name": "Resist Fire",
        "description": "Grants temporary resistance to fire.",
        "mana_cost": 10,
        "cooldown": 15.0,
        "effect_type": "apply_effect",
        "target_type": "friendly",
        "level_required": 4,
        "cast_message": "{caster_name} creates a shimmering, heat-resistant barrier.",
        "hit_message": "{target_name} is shielded from fire.",
        "dot_duration": 60.0,
        "effect_data": {
            "type": "stat_mod",
            "name": "Resist Fire",
            "modifiers": { "resist_fire": 25 }
        }
    }
}